sdk/__init__.py
sdk/progressively.py
sdk_progressively-0.0.2.dist-info/METADATA
sdk_progressively-0.0.2.dist-info/WHEEL
sdk_progressively-0.0.2.dist-info/top_level.txt
sdk_progressively-0.0.2.dist-info/RECORD
