Metadata-Version: 2.1
Name: sdk-progressively
Version: 0.0.2
Summary: Python SDK for Progressively
Author: Marvin Frachet <marvin.frachet@gmail.com>
License: MIT
Requires-Dist: requests
